feature_preprocessor/preprocessor.py
prepo/__init__.py
prepo/cli.py
prepo/io.py
prepo/preprocessor.py
prepo/types.py
prepo-0.2.0.dist-info/licenses/LICENSE
prepo-0.2.0.dist-info/METADATA
prepo-0.2.0.dist-info/WHEEL
prepo-0.2.0.dist-info/entry_points.txt
prepo-0.2.0.dist-info/top_level.txt
prepo-0.2.0.dist-info/RECORD
